videoboard/__init__.py
videoboard/__main__.py
videoboard/template.py
videoboard-0.1.1.dist-info/LICENSE.txt
videoboard-0.1.1.dist-info/METADATA
videoboard-0.1.1.dist-info/RECORD
videoboard-0.1.1.dist-info/WHEEL
videoboard-0.1.1.dist-info/entry_points.txt
videoboard-0.1.1.dist-info/top_level.txt
