Metadata-Version: 2.1
Name: videoboard
Version: 0.1.1
Summary: Launch a simple http server for visualizing videos and images
Home-page: https://github.com/youngwoon/videoboard
Author: Youngwoon Lee
Author-email: lywoon89@gmail.com
License: MIT
Keywords: http.server video image
Platform: UNKNOWN
Classifier: Development Status :: 3 - Alpha
Classifier: License :: OSI Approved :: MIT License
Classifier: Operating System :: POSIX :: Linux
Classifier: Programming Language :: Python :: 3
Classifier: Topic :: Internet :: WWW/HTTP :: HTTP Servers
Requires-Python: >=3
